manifests/__init__.py
manifests/py.typed
manifests-0.0.0.dist-info/LICENSE
manifests-0.0.0.dist-info/METADATA
manifests-0.0.0.dist-info/WHEEL
manifests-0.0.0.dist-info/RECORD
