Metadata-Version: 2.1
Name: manifests
Version: 0.0.0
Summary: Generate code from JSON manifests.
Home-page: https://github.com/bswck/manifests
License: MIT
Author: bswck
Author-email: bswck.dev@gmail.com
Requires-Python: >=3.8,<=3.12
Classifier: License :: OSI Approved :: MIT License
Classifier: Programming Language :: Python :: 3
Classifier: Programming Language :: Python :: 3.8
Classifier: Programming Language :: Python :: 3.9
Classifier: Programming Language :: Python :: 3.10
Classifier: Programming Language :: Python :: 3.11
Classifier: Programming Language :: Python :: 3.12
Project-URL: Coverage, https://coverage-badge.samuelcolvin.workers.dev/redirect/bswck/manifests
Project-URL: Documentation, https://manifests.readthedocs.io/en/latest/
Project-URL: Distribution, https://pypi.org/project/manifests/
Project-URL: Issues, https://github.com/bswck/manifests/issues
